cloud_logging_handler/__init__.py
cloud_logging_handler/handler.py
cloud_logging_handler/py.typed
cloud_logging_handler-0.2.5.dist-info/METADATA
cloud_logging_handler-0.2.5.dist-info/WHEEL
cloud_logging_handler-0.2.5.dist-info/licenses/LICENSE
cloud_logging_handler-0.2.5.dist-info/RECORD
