Metadata-Version: 2.4
Name: cloud-logging-handler
Version: 0.2.5
Summary: A Python logging handler for Google Cloud Logging with request tracing support
Project-URL: Homepage, https://github.com/loplat/gcp-cloud-logging-handler
Project-URL: Documentation, https://github.com/loplat/gcp-cloud-logging-handler#readme
Project-URL: Repository, https://github.com/loplat/gcp-cloud-logging-handler
Project-URL: Issues, https://github.com/loplat/gcp-cloud-logging-handler/issues
Project-URL: Changelog, https://github.com/loplat/gcp-cloud-logging-handler/blob/main/CHANGELOG.md
Author-email: loplat <dev@loplat.com>
License: MIT
License-File: LICENSE
Keywords: cloud-logging,gcp,google-cloud,logging,structured-logging,tracing
Classifier: Development Status :: 4 - Beta
Classifier: Intended Audience :: Developers
Classifier: License :: OSI Approved :: MIT License
Classifier: Operating System :: OS Independent
Classifier: Programming Language :: Python :: 3
Classifier: Programming Language :: Python :: 3.10
Classifier: Programming Language :: Python :: 3.11
Classifier: Programming Language :: Python :: 3.12
Classifier: Topic :: Internet :: Log Analysis
Classifier: Topic :: System :: Logging
Requires-Python: >=3.10
Provides-Extra: dev
Requires-Dist: pytest-asyncio>=0.21.0; extra == 'dev'
Requires-Dist: pytest>=7.0.0; extra == 'dev'
Requires-Dist: ruff>=0.1.0; extra == 'dev'
